qgate_sln_mlrun/__init__.py
qgate_sln_mlrun/output.py
qgate_sln_mlrun/qualityreport.py
qgate_sln_mlrun/setup.py
qgate_sln_mlrun/version.py
qgate_sln_mlrun/helper/__init__.py
qgate_sln_mlrun/helper/basehelper.py
qgate_sln_mlrun/helper/featuresethelper.py
qgate_sln_mlrun/helper/generateid.py
qgate_sln_mlrun/helper/kafkahelper.py
qgate_sln_mlrun/helper/mysqlhelper.py
qgate_sln_mlrun/helper/pipelinehelper.py
qgate_sln_mlrun/model_changes/__init__.py
qgate_sln_mlrun/model_changes/empty-template.json
qgate_sln_mlrun/templates/__init__.py
qgate_sln_mlrun/templates/qgt-mlrun.html
qgate_sln_mlrun/templates/qgt-mlrun.txt
qgate_sln_mlrun/ts/__init__.py
qgate_sln_mlrun/ts/tsbase.py
qgate_sln_mlrun/ts/tshelper.py
qgate_sln_mlrun/ts/ts01_project/__init__.py
qgate_sln_mlrun/ts/ts01_project/ts101.py
qgate_sln_mlrun/ts/ts01_project/ts102.py
qgate_sln_mlrun/ts/ts02_feature_set/__init__.py
qgate_sln_mlrun/ts/ts02_feature_set/ts201.py
qgate_sln_mlrun/ts/ts02_feature_set/ts202.py
qgate_sln_mlrun/ts/ts02_feature_set/ts203.py
qgate_sln_mlrun/ts/ts02_feature_set/ts204.py
qgate_sln_mlrun/ts/ts02_feature_set/ts205.py
qgate_sln_mlrun/ts/ts02_feature_set/ts206.py
qgate_sln_mlrun/ts/ts02_feature_set/ts207.py
qgate_sln_mlrun/ts/ts03_ingest_data/__init__.py
qgate_sln_mlrun/ts/ts03_ingest_data/ts301.py
qgate_sln_mlrun/ts/ts03_ingest_data/ts302.py
qgate_sln_mlrun/ts/ts03_ingest_data/ts303.py
qgate_sln_mlrun/ts/ts03_ingest_data/ts304.py
qgate_sln_mlrun/ts/ts03_ingest_data/ts305.py
qgate_sln_mlrun/ts/ts03_ingest_data/ts306.py
qgate_sln_mlrun/ts/ts04_ingest_data_pipeline/__init__.py
qgate_sln_mlrun/ts/ts04_ingest_data_pipeline/ts401.py
qgate_sln_mlrun/ts/ts04_ingest_data_pipeline/ts402.py
qgate_sln_mlrun/ts/ts04_ingest_data_pipeline/ts403.py
qgate_sln_mlrun/ts/ts04_ingest_data_pipeline/ts404.py
qgate_sln_mlrun/ts/ts04_ingest_data_pipeline/ts405.py
qgate_sln_mlrun/ts/ts05_feature_vector/__init__.py
qgate_sln_mlrun/ts/ts05_feature_vector/ts501.py
qgate_sln_mlrun/ts/ts06_get_data/__init__.py
qgate_sln_mlrun-0.2.8.dist-info/LICENSE
qgate_sln_mlrun-0.2.8.dist-info/METADATA
qgate_sln_mlrun-0.2.8.dist-info/WHEEL
qgate_sln_mlrun-0.2.8.dist-info/top_level.txt
qgate_sln_mlrun-0.2.8.dist-info/RECORD
