Metadata-Version: 2.1
Name: qgate_sln_mlrun
Version: 0.2.8
Summary: The quality gate for testing MLRun/Iguazio solution.
Author-email: Jiri Steuer <steuer.jiri@gmail.com>
Maintainer-email: Jiri Steuer <steuer.jiri@gmail.com>
License: MIT
Project-URL: homepage, https://github.com/george0st/qgate-sln-mlrun/
Project-URL: repository, https://pypi.org/project/qgate-sln-mlrun/
Keywords: testing,data-science,machine-learning,quality-assurance,quality-assessment,iguazio,mlrun,mlops,quality-gate,feature-store
Classifier: Development Status :: 3 - Alpha
Classifier: Intended Audience :: Developers
Classifier: License :: OSI Approved :: Apache Software License
Classifier: Operating System :: POSIX :: Linux
Classifier: Operating System :: Microsoft :: Windows
Classifier: Operating System :: MacOS
Classifier: Programming Language :: Python :: 3
Classifier: Programming Language :: Python :: 3.6
Classifier: Programming Language :: Python :: 3.7
Classifier: Programming Language :: Python :: 3.8
Classifier: Programming Language :: Python :: 3.9
Classifier: Programming Language :: Python :: 3.10
Classifier: Programming Language :: Python :: 3.11
Classifier: Programming Language :: Python :: 3 :: Only
Classifier: Programming Language :: Python
Classifier: Topic :: Software Development :: Libraries :: Python Modules
Classifier: Topic :: Software Development :: Libraries
Requires-Python: >=3.6
License-File: LICENSE
Requires-Dist: mlrun==1.6.4
Requires-Dist: python-dotenv~=0.17.0
Requires-Dist: jinja2~=3.1
Requires-Dist: scikit-learn==1.5.0
Requires-Dist: redis~=5.0
Requires-Dist: sqlalchemy~=1.4
Requires-Dist: cryptography~=42.0
Requires-Dist: pymysql~=1.1
Requires-Dist: psycopg2~=2.9
Requires-Dist: kafka-python~=2.0
Requires-Dist: avro~=1.11
Provides-Extra: dev
Requires-Dist: mlrun==1.6.4; extra == "dev"
Requires-Dist: python-dotenv~=0.17.0; extra == "dev"
Requires-Dist: jinja2~=3.1; extra == "dev"
Requires-Dist: scikit-learn==1.5.0; extra == "dev"
Requires-Dist: redis~=5.0; extra == "dev"
Requires-Dist: sqlalchemy~=1.4; extra == "dev"
Requires-Dist: cryptography~=42.0; extra == "dev"
Requires-Dist: pymysql~=1.1; extra == "dev"
Requires-Dist: psycopg2~=2.9; extra == "dev"
Requires-Dist: coverage~=7.5; extra == "dev"
Requires-Dist: coverage-badge>=1; extra == "dev"
